core/__init__.py
core/directions.py
core/formatter.py
core/game.py
core/generator.py
core/validator.py
core/word.py
core/wordlist.py
mask/__init__.py
mask/bitmap.py
mask/ellipse.py
mask/polygon.py
mask/shapes.py
word_search/__init__.py
word_search/_formatter.py
word_search/_generator.py
word_search/word_search.py
word_search_generator_but_tweaked-0.1.0.dist-info/METADATA
word_search_generator_but_tweaked-0.1.0.dist-info/WHEEL
word_search_generator_but_tweaked-0.1.0.dist-info/top_level.txt
word_search_generator_but_tweaked-0.1.0.dist-info/RECORD
