Metadata-Version: 2.4
Name: word_search_generator_but_tweaked
Version: 0.1.0
Summary: Generates pdf of word search but has title and can do it for large number of pages
Requires-Python: >=3.10
Requires-Dist: fpdf2==2.7.8
Requires-Dist: Pillow==11.0.0
Requires-Dist: rich==13.6.0
Requires-Dist: ordered-set>=4.0.0
Dynamic: description
Dynamic: requires-dist
Dynamic: requires-python
Dynamic: summary
